<?xml version="1.0" encoding="UTF-8" standalone="no" ?>
<Application>

  <Header>
    <Version val="14071.00"/>
    <WithIsn val="Y"/>
    <_InternalTask val="N"/>
    <IsRoot val="N"/>
    <InIndex val="N"/>
    <UniqueISNConvState val="12"/>
  </Header>

  <ProgramsRepository>
    <Programs>
      <Task MainProgram="N">
        <Header Description="DirektesAnmeldenpruefen" ISN_2="38" LastIsn="95" id="3321">
          <ExecutionRight comp="-1"/>
          <Resident val="Y"/>
          <SQL val="N"/>
          <ReturnValue>
            <ReturnValueAttr/>
            <TSK_PARAMS val="4"/>
            <ParametersAttributes>
              <Attr MgAttr="B"/>
              <Attr MgAttr="A"/>
              <Attr MgAttr="A"/>
              <Attr MgAttr="N"/>
            </ParametersAttributes>
          </ReturnValue>
          <SqlWhereExist val="N"/>
          <TaskType val="B"/>
          <External val="N"/>
          <Offline val="N"/>
          <FormType val="M"/>
          <DotNetObjectExists val="N"/>
          <LastModified _date="737895" _time="31807" date="15.04.2021" time="08:50:07"/>
        </Header>
        <ItemIsn val="15"/>
        <Resource>
          <Columns>
            <Column id="1" name="login_okay">
              <PropertyList model="FIELD">
                <Model attr_obj="FIELD_LOGICAL" id="1"/>
                <_FieldStyle id="276" val="1"/>
              </PropertyList>
            </Column>
            <Column id="5" name="Benutzername_p">
              <PropertyList model="FIELD">
                <Model attr_obj="FIELD_ALPHA" id="1"/>
                <Picture id="157" valUnicode="128"/>
                <StoredAs id="173" val="1"/>
                <Size id="174" val="128"/>
                <_Flip id="194"/>
              </PropertyList>
            </Column>
            <Column id="6" name="Passwort_p">
              <PropertyList model="FIELD">
                <Model attr_obj="FIELD_ALPHA" id="1"/>
                <Picture id="157" valUnicode="64"/>
                <StoredAs id="173" val="1"/>
                <Size id="174" val="64"/>
                <_Flip id="194"/>
              </PropertyList>
            </Column>
            <Column id="7" name="CloudContextInactivityTimeout_p">
              <PropertyList model="FIELD">
                <Model attr_obj="FIELD_NUMERIC" id="1"/>
                <Picture id="157" valUnicode="9Z"/>
                <_Dec id="181"/>
                <_Whole id="182" val="9"/>
                <_Negative id="192"/>
                <_FieldStyle id="276" val="1"/>
              </PropertyList>
            </Column>
            <Column id="2" name="ServerBenutzerGefunden">
              <PropertyList model="FIELD">
                <Model attr_obj="FIELD_LOGICAL" id="1"/>
                <_FieldStyle id="276" val="1"/>
              </PropertyList>
            </Column>
            <Column id="3" name="ServerBenutzerGesperrt">
              <PropertyList model="FIELD">
                <Model attr_obj="FIELD_LOGICAL" id="1"/>
                <_FieldStyle id="276" val="1"/>
              </PropertyList>
            </Column>
            <Column id="4" name="PasswortOK">
              <PropertyList model="FIELD">
                <Model attr_obj="FIELD_LOGICAL" id="1"/>
                <_FieldStyle id="276" val="1"/>
              </PropertyList>
            </Column>
          </Columns>
        </Resource>
        <Information>
          <Key>
            <Mode val="N"/>
          </Key>
          <DB comp="-1"/>
          <Sort>
            <CLS val="A"/>
          </Sort>
          <ForceRecordDelete DEL="N"/>
          <EndTaskCondition val="Y"/>
          <EvaluateEndCondition val="A"/>
          <InitialMode val="M"/>
          <Locate Direction="A"/>
          <Range Direction="A"/>
          <VarRange/>
          <TaskProperties>
            <SelectionTable val="N"/>
            <ConfirmUpdate CNFU="N"/>
            <ConfirmCancel val="N"/>
            <ErrorStrategy val="A"/>
            <LockingStrategy val="M"/>
            <CacheStrategy val="T"/>
            <ForceRecordSuffix val="N"/>
            <TransactionMode val="P"/>
            <TransactionBegin val="N"/>
            <PreloadView val="N"/>
            <AllowEmptyDataview val="N"/>
            <KeepCreatedContext val="N"/>
          </TaskProperties>
          <SIDE_WIN>
            <AllowOptions val="N"/>
            <AllowQuery val="Y"/>
            <AllowModify val="Y"/>
            <AllowCreate val="Y"/>
            <AllowDelete val="Y"/>
            <AllowLocate val="Y"/>
            <AllowRange val="Y"/>
            <AllowIndexChange val="Y"/>
            <AllowSorting val="Y"/>
            <AllowIOFiles val="N"/>
            <RecordCycle val="Y"/>
            <AllowEvents val="N"/>
            <AllowIndexOptimization val="Y"/>
            <AllowLocationInQuery val="Y"/>
            <AllowPrintingData val="N"/>
          </SIDE_WIN>
          <WIN>
            <OpenTaskWindow val="N"/>
            <CloseTaskWindow val="Y"/>
            <ForegroundWindow val="Y"/>
            <FlipFld val="N"/>
            <RefreshTaskWindow ReturnValue="N"/>
          </WIN>
          <BOX>
            <Direction val="V"/>
          </BOX>
        </Information>
        <TaskLogic>
          <LogicUnit id="2" propagate="78">
            <Level val="R"/>
            <Type val="M"/>
            <Scope val="S"/>
            <EngineDirective val="S"/>
            <ShowMessage val="Y"/>
            <Condition val="89"/>
            <Event>
              <EventType val="S"/>
            </Event>
            <LogicLines>
              <LogicLine>
                <DATAVIEW_SRC FlowIsn="2" Type="M">
                  <Condition val="N"/>
                  <Modifier val="B"/>
                  <Direction val="C"/>
                </DATAVIEW_SRC>
              </LogicLine>
              <LogicLine>
                <Select FieldID="1" FlowIsn="3" id="1">
                  <Column val="1"/>
                  <Type val="V"/>
                  <ExposedToRoute val="N"/>
                  <IsParameter val="Y"/>
                  <DIFF_UPDATE val="T"/>
                  <Condition val="Y"/>
                  <Modifier val="S"/>
                  <Direction val="C"/>
                </Select>
              </LogicLine>
              <LogicLine>
                <Select FieldID="11" FlowIsn="14" id="11">
                  <Column val="5"/>
                  <Type val="V"/>
                  <ExposedToRoute val="N"/>
                  <IsParameter val="Y"/>
                  <DIFF_UPDATE val="T"/>
                  <Condition val="N"/>
                  <Modifier val="S"/>
                  <Direction val="C"/>
                </Select>
              </LogicLine>
              <LogicLine>
                <Select FieldID="4" FlowIsn="7" id="4">
                  <Column val="6"/>
                  <Type val="V"/>
                  <ExposedToRoute val="N"/>
                  <IsParameter val="Y"/>
                  <DIFF_UPDATE val="T"/>
                  <Condition val="N"/>
                  <Modifier val="S"/>
                  <Direction val="C"/>
                </Select>
              </LogicLine>
              <LogicLine>
                <Select FieldID="15" FlowIsn="37" id="15">
                  <Column val="7"/>
                  <Type val="V"/>
                  <ExposedToRoute val="N"/>
                  <IsParameter val="Y"/>
                  <DIFF_UPDATE val="T"/>
                  <Condition val="Y"/>
                  <Modifier val="S"/>
                  <Direction val="C"/>
                </Select>
              </LogicLine>
              <LogicLine>
                <Select FieldID="12" FlowIsn="16" id="12">
                  <Column val="2"/>
                  <Type val="V"/>
                  <ExposedToRoute val="N"/>
                  <IsParameter val="N"/>
                  <DIFF_UPDATE val="T"/>
                  <Condition val="Y"/>
                  <Modifier val="S"/>
                  <Direction val="C"/>
                </Select>
              </LogicLine>
              <LogicLine>
                <Select FieldID="13" FlowIsn="17" id="13">
                  <Column val="3"/>
                  <Type val="V"/>
                  <ExposedToRoute val="N"/>
                  <IsParameter val="N"/>
                  <DIFF_UPDATE val="T"/>
                  <Condition val="Y"/>
                  <Modifier val="S"/>
                  <Direction val="C"/>
                </Select>
              </LogicLine>
              <LogicLine>
                <Select FieldID="14" FlowIsn="18" id="14">
                  <Column val="4"/>
                  <Type val="V"/>
                  <ExposedToRoute val="N"/>
                  <IsParameter val="N"/>
                  <DIFF_UPDATE val="T"/>
                  <Condition val="Y"/>
                  <Modifier val="S"/>
                  <Direction val="C"/>
                </Select>
              </LogicLine>
            </LogicLines>
          </LogicUnit>
          <LogicUnit id="3" propagate="78">
            <Level val="T"/>
            <Type val="S"/>
            <Scope val="S"/>
            <EngineDirective val="S"/>
            <ShowMessage val="Y"/>
            <Condition val="89"/>
            <Event>
              <EventType val="S"/>
            </Event>
            <Expanded val="1"/>
            <LogicLines>
              <LogicLine>
                <CallTask FlowIsn="19">
                  <OperationType val="T"/>
                  <Event>
                    <EventType val="N"/>
                  </Event>
                  <TaskID comp="-1" obj="94"/>
                  <Lock val="N"/>
                  <Arguments>
                    <Argument>
                      <Variable val="12"/>
                      <Skip val="N"/>
                    </Argument>
                    <Argument>
                      <Variable val="13"/>
                      <Skip val="N"/>
                    </Argument>
                    <Argument>
                      <Variable val="14"/>
                      <Skip val="N"/>
                    </Argument>
                  </Arguments>
                  <Wait val="Y"/>
                  <SyncData val="N"/>
                  <RetainFocus val="N"/>
                  <Condition val="Y"/>
                  <Modifier val="S"/>
                  <Direction val="C"/>
                </CallTask>
              </LogicLine>
              <LogicLine>
                <BLOCK EndBlock="36" EndBlockSegment="30" FlowIsn="20" Type="I">
                  <Expanded val="1"/>
                  <Condition Exp="2"/>
                  <Modifier val="B"/>
                  <Direction val="C"/>
                </BLOCK>
              </LogicLine>
              <LogicLine>
                <Update FlowIsn="27">
                  <FieldID val="1"/>
                  <WithValue val="10"/>
                  <Incremental val="N"/>
                  <ForcedUpdate val="Y"/>
                  <Condition val="Y"/>
                  <Modifier val="B"/>
                  <Direction val="C"/>
                </Update>
              </LogicLine>
              <LogicLine>
                <BLOCK EndBlock="36" EndBlockSegment="36" FlowIsn="30" Type="E">
                  <Expanded val="1"/>
                  <Condition val="Y"/>
                  <Modifier val="B"/>
                  <Direction val="C"/>
                </BLOCK>
              </LogicLine>
              <LogicLine>
                <Update FlowIsn="35">
                  <FieldID val="1"/>
                  <WithValue val="11"/>
                  <Incremental val="N"/>
                  <ForcedUpdate val="Y"/>
                  <Condition val="Y"/>
                  <Modifier val="B"/>
                  <Direction val="C"/>
                </Update>
              </LogicLine>
              <LogicLine>
                <END_BLK FlowIsn="36"/>
              </LogicLine>
            </LogicLines>
          </LogicUnit>
        </TaskLogic>
        <TaskForms>
          <FormEntry id="1">
            <PropertyList model="FORM_GUI0">
              <_Comment id="218"/>
              <FormName id="311" valUnicode="DirektesAnmeldenpruefen"/>
            </PropertyList>
          </FormEntry>
        </TaskForms>
        <Expressions>
          <Expression id="2">
            <ExpSyntax val="{0,12} AND NOT ({0,13}) AND {0,14}"/>
            <ExpAttribute val="B"/>
          </Expression>
          <Expression id="10">
            <ExpSyntax val="'TRUE'LOG"/>
            <ExpAttribute val="B"/>
          </Expression>
          <Expression id="11">
            <ExpSyntax val="'FALSE'LOG"/>
            <ExpAttribute val="B"/>
          </Expression>
        </Expressions>
        <Task MainProgram="N">
          <Header Description="Server Benutzer vorhanden" ISN_2="94" LastIsn="95" id="3321">
            <ExecutionRight comp="-1"/>
            <Resident val="Y"/>
            <SQL val="N"/>
            <ReturnValue>
              <ReturnValueAttr/>
              <TSK_PARAMS val="3"/>
              <ParametersAttributes>
                <Attr MgAttr="B"/>
                <Attr MgAttr="B"/>
                <Attr MgAttr="B"/>
              </ParametersAttributes>
            </ReturnValue>
            <SqlWhereExist val="N"/>
            <TaskType val="B"/>
            <External val="N"/>
            <FormType val="M"/>
            <DotNetObjectExists val="N"/>
            <LastModified _date="737895" _time="31807" date="15.04.2021" time="08:50:07"/>
          </Header>
          <ItemIsn val="43"/>
          <Resource>
            <DB id="3">
              <DataObject comp="2" obj="112"/>
              <Access val="R"/>
              <Share val="W"/>
              <Open val="N"/>
              <Cache val="Y"/>
              <IdentifyRowModifications val="84"/>
            </DB>
            <DB id="1">
              <DataObject comp="2" obj="4119"/>
              <Access val="R"/>
              <Share val="W"/>
              <Open val="N"/>
              <Cache val="Y"/>
              <IdentifyRowModifications val="84"/>
            </DB>
            <DB id="2">
              <DataObject comp="2" obj="4258"/>
              <Access val="R"/>
              <Share val="W"/>
              <Open val="N"/>
              <Cache val="Y"/>
              <IdentifyRowModifications val="84"/>
            </DB>
            <Columns>
              <Column id="1" name="BenutzerGefunden_p">
                <PropertyList model="FIELD">
                  <Model attr_obj="FIELD_LOGICAL" id="1"/>
                  <_FieldStyle id="276" val="1"/>
                </PropertyList>
              </Column>
              <Column id="2" name="BenztzerGesperrt_p">
                <PropertyList model="FIELD">
                  <Model attr_obj="FIELD_LOGICAL" id="1"/>
                  <_FieldStyle id="276" val="1"/>
                </PropertyList>
              </Column>
              <Column id="3" name="PW_OK_p">
                <PropertyList model="FIELD">
                  <Model attr_obj="FIELD_LOGICAL" id="1"/>
                  <_FieldStyle id="276" val="1"/>
                </PropertyList>
              </Column>
              <Column id="4" name="gefunden_retcd">
                <PropertyList model="FIELD">
                  <Model attr_obj="FIELD_LOGICAL" id="1"/>
                  <_FieldStyle id="276" val="1"/>
                </PropertyList>
              </Column>
            </Columns>
          </Resource>
          <Information>
            <Key>
              <Mode val="N"/>
            </Key>
            <DB comp="-1"/>
            <Sort>
              <CLS val="A"/>
            </Sort>
            <ForceRecordDelete DEL="N"/>
            <EndTaskCondition val="Y"/>
            <EvaluateEndCondition val="A"/>
            <InitialMode val="M"/>
            <Locate Direction="A"/>
            <Range Direction="A"/>
            <VarRange/>
            <TaskProperties>
              <SelectionTable val="N"/>
              <ConfirmUpdate CNFU="N"/>
              <ConfirmCancel val="N"/>
              <ErrorStrategy val="A"/>
              <LockingStrategy val="M"/>
              <CacheStrategy val="T"/>
              <ForceRecordSuffix val="N"/>
              <TransactionMode val="P"/>
              <TransactionBegin val="N"/>
              <PreloadView val="N"/>
              <AllowEmptyDataview val="N"/>
              <KeepCreatedContext val="N"/>
            </TaskProperties>
            <SIDE_WIN>
              <AllowOptions val="N"/>
              <AllowQuery val="Y"/>
              <AllowModify val="Y"/>
              <AllowCreate val="Y"/>
              <AllowDelete val="Y"/>
              <AllowLocate val="Y"/>
              <AllowRange val="Y"/>
              <AllowIndexChange val="Y"/>
              <AllowSorting val="Y"/>
              <AllowIOFiles val="N"/>
              <RecordCycle val="Y"/>
              <AllowEvents val="N"/>
              <AllowIndexOptimization val="Y"/>
              <AllowLocationInQuery val="Y"/>
              <AllowPrintingData val="N"/>
            </SIDE_WIN>
            <WIN>
              <OpenTaskWindow val="N"/>
              <CloseTaskWindow val="Y"/>
              <ForegroundWindow val="Y"/>
              <FlipFld val="N"/>
              <RefreshTaskWindow ReturnValue="N"/>
            </WIN>
            <BOX>
              <Direction val="V"/>
            </BOX>
          </Information>
          <INT_CMP_LIST_INFO>
            <v>3</v>
            <v>2</v>
          </INT_CMP_LIST_INFO>
          <TaskLogic>
            <LogicUnit id="2" propagate="78">
              <Level val="R"/>
              <Type val="M"/>
              <Scope val="S"/>
              <EngineDirective val="S"/>
              <ShowMessage val="Y"/>
              <Condition val="89"/>
              <Event>
                <EventType val="S"/>
              </Event>
              <LogicLines>
                <LogicLine>
                  <DATAVIEW_SRC FlowIsn="2" Type="M">
                    <Condition val="N"/>
                    <Modifier val="B"/>
                    <Direction val="C"/>
                  </DATAVIEW_SRC>
                </LogicLine>
                <LogicLine>
                  <Select FieldID="1" FlowIsn="3" id="1">
                    <Column val="1"/>
                    <Type val="V"/>
                    <ExposedToRoute val="N"/>
                    <IsParameter val="Y"/>
                    <DIFF_UPDATE val="T"/>
                    <Condition val="Y"/>
                    <Modifier val="S"/>
                    <Direction val="C"/>
                  </Select>
                </LogicLine>
                <LogicLine>
                  <Select FieldID="2" FlowIsn="4" id="2">
                    <Column val="2"/>
                    <Type val="V"/>
                    <ExposedToRoute val="N"/>
                    <IsParameter val="Y"/>
                    <DIFF_UPDATE val="T"/>
                    <Condition val="Y"/>
                    <Modifier val="S"/>
                    <Direction val="C"/>
                  </Select>
                </LogicLine>
                <LogicLine>
                  <Select FieldID="3" FlowIsn="5" id="3">
                    <Column val="3"/>
                    <Type val="V"/>
                    <ExposedToRoute val="N"/>
                    <IsParameter val="Y"/>
                    <DIFF_UPDATE val="T"/>
                    <Condition val="Y"/>
                    <Modifier val="S"/>
                    <Direction val="C"/>
                  </Select>
                </LogicLine>
                <LogicLine>
                  <Select FieldID="4" FlowIsn="6" id="4">
                    <Column val="4"/>
                    <Type val="V"/>
                    <ExposedToRoute val="N"/>
                    <IsParameter val="N"/>
                    <DIFF_UPDATE val="T"/>
                    <Condition val="Y"/>
                    <Modifier val="S"/>
                    <Direction val="C"/>
                  </Select>
                </LogicLine>
                <LogicLine>
                  <LNK Direction="A" EVL_CND="R" FieldID="4" FlowIsn="7" Key="1" Mode="R" SortType="19" VIEW="5" VIEWS="12">
                    <DB comp="2" obj="4119"/>
                    <Expanded val="1"/>
                    <Condition val="Y"/>
                  </LNK>
                </LogicLine>
                <LogicLine>
                  <Select FieldID="5" FlowIsn="8" id="5">
                    <Column val="1"/>
                    <Type val="R"/>
                    <ExposedToRoute val="N"/>
                    <IsParameter val="N"/>
                    <Locate MAX="1" MIN="1"/>
                    <DIFF_UPDATE val="T"/>
                    <Condition val="N"/>
                    <Modifier val="S"/>
                    <Direction val="C"/>
                  </Select>
                </LogicLine>
                <LogicLine>
                  <Select FieldID="6" FlowIsn="9" id="6">
                    <Column val="19"/>
                    <Type val="R"/>
                    <ExposedToRoute val="N"/>
                    <IsParameter val="N"/>
                    <DIFF_UPDATE val="T"/>
                    <Condition val="N"/>
                    <Modifier val="S"/>
                    <Direction val="C"/>
                  </Select>
                </LogicLine>
                <LogicLine>
                  <Select FieldID="7" FlowIsn="10" id="7">
                    <Column val="2"/>
                    <Type val="R"/>
                    <ExposedToRoute val="N"/>
                    <IsParameter val="N"/>
                    <DIFF_UPDATE val="T"/>
                    <Condition val="N"/>
                    <Modifier val="S"/>
                    <Direction val="C"/>
                  </Select>
                </LogicLine>
                <LogicLine>
                  <Select FieldID="8" FlowIsn="11" id="8">
                    <Column val="24"/>
                    <Type val="R"/>
                    <ExposedToRoute val="N"/>
                    <IsParameter val="N"/>
                    <INT_RCMP_INFO>
                      <v>250</v>
                      <v>300</v>
                    </INT_RCMP_INFO>
                    <DIFF_UPDATE val="T"/>
                    <Condition val="N"/>
                    <Modifier val="S"/>
                    <Direction val="C"/>
                  </Select>
                </LogicLine>
                <LogicLine>
                  <Select FieldID="9" FlowIsn="12" id="9">
                    <Column val="25"/>
                    <Type val="R"/>
                    <ExposedToRoute val="N"/>
                    <IsParameter val="N"/>
                    <INT_RCMP_INFO>
                      <v>250</v>
                      <v>300</v>
                    </INT_RCMP_INFO>
                    <DIFF_UPDATE val="T"/>
                    <Condition val="N"/>
                    <Modifier val="S"/>
                    <Direction val="C"/>
                  </Select>
                </LogicLine>
                <LogicLine>
                  <Select FieldID="10" FlowIsn="13" id="10">
                    <Column val="26"/>
                    <Type val="R"/>
                    <ExposedToRoute val="N"/>
                    <IsParameter val="N"/>
                    <INT_RCMP_INFO>
                      <v>250</v>
                      <v>300</v>
                    </INT_RCMP_INFO>
                    <DIFF_UPDATE val="T"/>
                    <Condition val="N"/>
                    <Modifier val="S"/>
                    <Direction val="C"/>
                  </Select>
                </LogicLine>
                <LogicLine>
                  <Select FieldID="11" FlowIsn="14" id="11">
                    <Column val="27"/>
                    <Type val="R"/>
                    <ExposedToRoute val="N"/>
                    <IsParameter val="N"/>
                    <INT_RCMP_INFO>
                      <v>250</v>
                      <v>300</v>
                    </INT_RCMP_INFO>
                    <DIFF_UPDATE val="T"/>
                    <Condition val="N"/>
                    <Modifier val="S"/>
                    <Direction val="C"/>
                  </Select>
                </LogicLine>
                <LogicLine>
                  <Select FieldID="12" FlowIsn="15" id="12">
                    <Column val="28"/>
                    <Type val="R"/>
                    <ExposedToRoute val="N"/>
                    <IsParameter val="N"/>
                    <DIFF_UPDATE val="T"/>
                    <Condition val="N"/>
                    <Modifier val="S"/>
                    <Direction val="C"/>
                  </Select>
                </LogicLine>
                <LogicLine>
                  <Select FieldID="13" FlowIsn="16" id="13">
                    <Column val="29"/>
                    <Type val="R"/>
                    <ExposedToRoute val="N"/>
                    <IsParameter val="N"/>
                    <DIFF_UPDATE val="T"/>
                    <Condition val="N"/>
                    <Modifier val="S"/>
                    <Direction val="C"/>
                  </Select>
                </LogicLine>
                <LogicLine>
                  <Select FieldID="14" FlowIsn="17" id="14">
                    <Column val="30"/>
                    <Type val="R"/>
                    <ExposedToRoute val="N"/>
                    <IsParameter val="N"/>
                    <DIFF_UPDATE val="T"/>
                    <Condition val="N"/>
                    <Modifier val="S"/>
                    <Direction val="C"/>
                  </Select>
                </LogicLine>
                <LogicLine>
                  <Select FieldID="15" FlowIsn="18" id="15">
                    <Column val="31"/>
                    <Type val="R"/>
                    <ExposedToRoute val="N"/>
                    <IsParameter val="N"/>
                    <DIFF_UPDATE val="T"/>
                    <Condition val="N"/>
                    <Modifier val="S"/>
                    <Direction val="C"/>
                  </Select>
                </LogicLine>
                <LogicLine>
                  <Select FieldID="37" FlowIsn="299" id="37">
                    <Column val="36"/>
                    <Type val="R"/>
                    <ExposedToRoute val="N"/>
                    <IsParameter val="N"/>
                    <DIFF_UPDATE val="T"/>
                    <Condition val="N"/>
                    <Modifier val="S"/>
                    <Direction val="C"/>
                  </Select>
                </LogicLine>
                <LogicLine>
                  <END_LINK FlowIsn="19"/>
                </LogicLine>
                <LogicLine>
                  <LNK Direction="A" EVL_CND="R" FlowIsn="250" Key="1" Mode="R" SortType="251" VIEW="17" VIEWS="6">
                    <DB comp="2" obj="4258"/>
                    <Expanded val="1"/>
                    <Condition val="Y"/>
                  </LNK>
                </LogicLine>
                <LogicLine>
                  <Select FieldID="35" FlowIsn="256" id="35">
                    <Column val="1"/>
                    <Type val="R"/>
                    <ExposedToRoute val="N"/>
                    <IsParameter val="N"/>
                    <Locate MAX="1" MIN="1"/>
                    <DIFF_UPDATE val="T"/>
                    <Condition val="N"/>
                    <Modifier val="S"/>
                    <Direction val="C"/>
                  </Select>
                </LogicLine>
                <LogicLine>
                  <Select FieldID="34" FlowIsn="255" id="34">
                    <Column val="34"/>
                    <Type val="R"/>
                    <ExposedToRoute val="N"/>
                    <IsParameter val="N"/>
                    <Locate MAX="29" MIN="29"/>
                    <DIFF_UPDATE val="T"/>
                    <Condition val="N"/>
                    <Modifier val="S"/>
                    <Direction val="C"/>
                  </Select>
                </LogicLine>
                <LogicLine>
                  <Select FieldID="33" FlowIsn="254" id="33">
                    <Column val="35"/>
                    <Type val="R"/>
                    <ExposedToRoute val="N"/>
                    <IsParameter val="N"/>
                    <Locate MAX="9" MIN="9"/>
                    <DIFF_UPDATE val="T"/>
                    <Condition val="N"/>
                    <Modifier val="S"/>
                    <Direction val="C"/>
                  </Select>
                </LogicLine>
                <LogicLine>
                  <Select FieldID="32" FlowIsn="253" id="32">
                    <Column val="36"/>
                    <Type val="R"/>
                    <ExposedToRoute val="N"/>
                    <IsParameter val="N"/>
                    <Locate MAX="10" MIN="10"/>
                    <DIFF_UPDATE val="T"/>
                    <Condition val="N"/>
                    <Modifier val="S"/>
                    <Direction val="C"/>
                  </Select>
                </LogicLine>
                <LogicLine>
                  <Select FieldID="31" FlowIsn="252" id="31">
                    <Column val="37"/>
                    <Type val="R"/>
                    <ExposedToRoute val="N"/>
                    <IsParameter val="N"/>
                    <Locate MAX="11" MIN="11"/>
                    <DIFF_UPDATE val="T"/>
                    <Condition val="N"/>
                    <Modifier val="S"/>
                    <Direction val="C"/>
                  </Select>
                </LogicLine>
                <LogicLine>
                  <Select FieldID="36" FlowIsn="257" id="36">
                    <Column val="38"/>
                    <Type val="R"/>
                    <ExposedToRoute val="N"/>
                    <IsParameter val="N"/>
                    <DIFF_UPDATE val="T"/>
                    <Condition val="N"/>
                    <Modifier val="S"/>
                    <Direction val="C"/>
                  </Select>
                </LogicLine>
                <LogicLine>
                  <END_LINK FlowIsn="251"/>
                </LogicLine>
                <LogicLine>
                  <LNK Direction="A" EVL_CND="R" FlowIsn="300" Key="1" Mode="R" SortType="301" VIEW="23" VIEWS="6">
                    <DB comp="2" obj="112"/>
                    <Expanded val="1"/>
                    <Condition val="Y"/>
                  </LNK>
                </LogicLine>
                <LogicLine>
                  <Select FieldID="42" FlowIsn="306" id="42">
                    <Column val="1"/>
                    <Type val="R"/>
                    <ExposedToRoute val="N"/>
                    <IsParameter val="N"/>
                    <Locate MAX="29" MIN="29"/>
                    <DIFF_UPDATE val="T"/>
                    <Condition val="N"/>
                    <Modifier val="S"/>
                    <Direction val="C"/>
                  </Select>
                </LogicLine>
                <LogicLine>
                  <Select FieldID="41" FlowIsn="305" id="41">
                    <Column val="2"/>
                    <Type val="R"/>
                    <ExposedToRoute val="N"/>
                    <IsParameter val="N"/>
                    <Locate MAX="9" MIN="9"/>
                    <DIFF_UPDATE val="T"/>
                    <Condition val="N"/>
                    <Modifier val="S"/>
                    <Direction val="C"/>
                  </Select>
                </LogicLine>
                <LogicLine>
                  <Select FieldID="40" FlowIsn="304" id="40">
                    <Column val="3"/>
                    <Type val="R"/>
                    <ExposedToRoute val="N"/>
                    <IsParameter val="N"/>
                    <Locate MAX="10" MIN="10"/>
                    <DIFF_UPDATE val="T"/>
                    <Condition val="N"/>
                    <Modifier val="S"/>
                    <Direction val="C"/>
                  </Select>
                </LogicLine>
                <LogicLine>
                  <Select FieldID="39" FlowIsn="303" id="39">
                    <Column val="4"/>
                    <Type val="R"/>
                    <ExposedToRoute val="N"/>
                    <IsParameter val="N"/>
                    <Locate MAX="11" MIN="11"/>
                    <DIFF_UPDATE val="T"/>
                    <Condition val="N"/>
                    <Modifier val="S"/>
                    <Direction val="C"/>
                  </Select>
                </LogicLine>
                <LogicLine>
                  <Select FieldID="38" FlowIsn="302" id="38">
                    <Column val="5"/>
                    <Type val="R"/>
                    <ExposedToRoute val="N"/>
                    <IsParameter val="N"/>
                    <Locate MAX="30" MIN="30"/>
                    <DIFF_UPDATE val="T"/>
                    <Condition val="N"/>
                    <Modifier val="S"/>
                    <Direction val="C"/>
                  </Select>
                </LogicLine>
                <LogicLine>
                  <Select FieldID="43" FlowIsn="307" id="43">
                    <Column val="70"/>
                    <Type val="R"/>
                    <ExposedToRoute val="N"/>
                    <IsParameter val="N"/>
                    <DIFF_UPDATE val="T"/>
                    <Condition val="N"/>
                    <Modifier val="S"/>
                    <Direction val="C"/>
                  </Select>
                </LogicLine>
                <LogicLine>
                  <END_LINK FlowIsn="301"/>
                </LogicLine>
                <LogicLine>
                  <Remark FlowIsn="176">
                    <Type val="0"/>
                    <Text val="Problem: die ZEbene ist noch nicht gesetzt"/>
                  </Remark>
                </LogicLine>
                <LogicLine>
                  <Remark FlowIsn="178">
                    <Type val="0"/>
                    <Text val="Mitarbeiter lesen über Untertask"/>
                  </Remark>
                </LogicLine>
              </LogicLines>
            </LogicUnit>
            <LogicUnit id="3" propagate="78">
              <Level val="R"/>
              <Type val="S"/>
              <Scope val="S"/>
              <EngineDirective val="S"/>
              <ShowMessage val="Y"/>
              <Condition val="89"/>
              <Event>
                <EventType val="S"/>
              </Event>
              <Expanded val="1"/>
              <LogicLines>
                <LogicLine>
                  <Update FlowIsn="137">
                    <FieldID val="3"/>
                    <WithValue val="25"/>
                    <Incremental val="N"/>
                    <ForcedUpdate val="Y"/>
                    <Condition val="Y"/>
                    <Modifier val="B"/>
                    <Direction val="C"/>
                  </Update>
                </LogicLine>
                <LogicLine>
                  <CallTask FlowIsn="39">
                    <OperationType val="P"/>
                    <Event>
                      <EventType val="N"/>
                    </Event>
                    <TaskID comp="-1" obj="3007"/>
                    <Lock val="N"/>
                    <Arguments>
                      <Argument>
                        <Expression val="16"/>
                        <Skip val="N"/>
                      </Argument>
                    </Arguments>
                    <Wait val="Y"/>
                    <SyncData val="N"/>
                    <RetainFocus val="N"/>
                    <Condition Exp="27"/>
                    <Modifier val="B"/>
                    <Direction val="C"/>
                  </CallTask>
                </LogicLine>
                <LogicLine>
                  <Update FlowIsn="20">
                    <FieldID val="1"/>
                    <WithValue val="2"/>
                    <Incremental val="N"/>
                    <ForcedUpdate val="Y"/>
                    <Condition val="Y"/>
                    <Modifier val="B"/>
                    <Direction val="C"/>
                  </Update>
                </LogicLine>
                <LogicLine>
                  <Update FlowIsn="21">
                    <FieldID val="2"/>
                    <WithValue val="3"/>
                    <Incremental val="N"/>
                    <ForcedUpdate val="Y"/>
                    <Condition val="Y"/>
                    <Modifier val="B"/>
                    <Direction val="C"/>
                  </Update>
                </LogicLine>
                <LogicLine>
                  <Remark FlowIsn="98">
                    <Type val="2"/>
                    <Text val="Leeres PW verschlüsselt=daibv7Kq5Mk/ZYSaTsugIg=="/>
                  </Remark>
                </LogicLine>
                <LogicLine>
                  <Update FlowIsn="22">
                    <FieldID val="3"/>
                    <WithValue val="4"/>
                    <Incremental val="N"/>
                    <ForcedUpdate val="Y"/>
                    <Condition val="Y"/>
                    <Modifier val="B"/>
                    <Direction val="C"/>
                  </Update>
                </LogicLine>
                <LogicLine>
                  <CallTask FlowIsn="118">
                    <OperationType val="P"/>
                    <Event>
                      <EventType val="N"/>
                    </Event>
                    <TaskID comp="-1" obj="3007"/>
                    <Lock val="N"/>
                    <Arguments>
                      <Argument>
                        <Expression val="24"/>
                        <Skip val="N"/>
                      </Argument>
                    </Arguments>
                    <Wait val="Y"/>
                    <SyncData val="N"/>
                    <RetainFocus val="N"/>
                    <Condition Exp="27"/>
                    <Modifier val="S"/>
                    <Direction val="C"/>
                  </CallTask>
                </LogicLine>
                <LogicLine>
                  <BLOCK EndBlock="26" EndBlockSegment="26" FlowIsn="23" Type="I">
                    <Expanded val="1"/>
                    <Condition Exp="5"/>
                    <Modifier val="B"/>
                    <Direction val="C"/>
                  </BLOCK>
                </LogicLine>
                <LogicLine>
                  <Remark FlowIsn="24">
                    <Type val="2"/>
                    <Text val="Versuche AD Login"/>
                  </Remark>
                </LogicLine>
                <LogicLine>
                  <Evaluate FlowIsn="25">
                    <Expression val="6"/>
                    <FieldID val="3"/>
                    <Disabled val="1"/>
                    <Condition val="Y"/>
                    <Modifier val="B"/>
                    <Direction val="C"/>
                  </Evaluate>
                </LogicLine>
                <LogicLine>
                  <END_BLK FlowIsn="26"/>
                </LogicLine>
                <LogicLine>
                  <BLOCK EndBlock="38" EndBlockSegment="38" FlowIsn="27" Type="I">
                    <Expanded val="1"/>
                    <Condition Exp="7"/>
                    <Modifier val="B"/>
                    <Direction val="C"/>
                  </BLOCK>
                </LogicLine>
                <LogicLine>
                  <Update FlowIsn="28">
                    <Parent val="32768"/>
                    <FieldID val="1"/>
                    <WithValue val="8"/>
                    <Incremental val="N"/>
                    <ForcedUpdate val="Y"/>
                    <Condition val="Y"/>
                    <Modifier val="B"/>
                    <Direction val="C"/>
                  </Update>
                </LogicLine>
                <LogicLine>
                  <Update FlowIsn="29">
                    <Parent val="32768"/>
                    <FieldID val="2"/>
                    <WithValue val="9"/>
                    <Incremental val="N"/>
                    <ForcedUpdate val="Y"/>
                    <Condition val="Y"/>
                    <Modifier val="B"/>
                    <Direction val="C"/>
                  </Update>
                </LogicLine>
                <LogicLine>
                  <Update FlowIsn="30">
                    <Parent val="32768"/>
                    <FieldID val="3"/>
                    <WithValue val="10"/>
                    <Incremental val="N"/>
                    <ForcedUpdate val="Y"/>
                    <Condition val="Y"/>
                    <Modifier val="B"/>
                    <Direction val="C"/>
                  </Update>
                </LogicLine>
                <LogicLine>
                  <Update FlowIsn="31">
                    <Parent val="32768"/>
                    <FieldID val="4"/>
                    <WithValue val="11"/>
                    <Incremental val="N"/>
                    <ForcedUpdate val="Y"/>
                    <Condition val="Y"/>
                    <Modifier val="B"/>
                    <Direction val="C"/>
                  </Update>
                </LogicLine>
                <LogicLine>
                  <Update FlowIsn="32">
                    <Parent val="32768"/>
                    <FieldID val="5"/>
                    <WithValue val="12"/>
                    <Incremental val="N"/>
                    <ForcedUpdate val="Y"/>
                    <Condition val="Y"/>
                    <Modifier val="B"/>
                    <Direction val="C"/>
                  </Update>
                </LogicLine>
                <LogicLine>
                  <Update FlowIsn="33">
                    <Parent val="32768"/>
                    <FieldID val="6"/>
                    <WithValue val="13"/>
                    <Incremental val="N"/>
                    <ForcedUpdate val="Y"/>
                    <Condition val="Y"/>
                    <Modifier val="B"/>
                    <Direction val="C"/>
                  </Update>
                </LogicLine>
                <LogicLine>
                  <Update FlowIsn="34">
                    <Parent val="32768"/>
                    <FieldID val="7"/>
                    <WithValue val="14"/>
                    <Incremental val="N"/>
                    <ForcedUpdate val="Y"/>
                    <Condition val="Y"/>
                    <Modifier val="B"/>
                    <Direction val="C"/>
                  </Update>
                </LogicLine>
                <LogicLine>
                  <Update FlowIsn="35">
                    <Parent val="32768"/>
                    <FieldID val="8"/>
                    <WithValue val="15"/>
                    <Incremental val="N"/>
                    <ForcedUpdate val="Y"/>
                    <Condition val="Y"/>
                    <Modifier val="B"/>
                    <Direction val="C"/>
                  </Update>
                </LogicLine>
                <LogicLine>
                  <Update FlowIsn="163">
                    <Parent val="32768"/>
                    <FieldID val="9"/>
                    <WithValue val="8"/>
                    <Incremental val="N"/>
                    <ForcedUpdate val="Y"/>
                    <Condition val="Y"/>
                    <Modifier val="B"/>
                    <Direction val="C"/>
                  </Update>
                </LogicLine>
                <LogicLine>
                  <Update FlowIsn="164">
                    <Parent val="32768"/>
                    <FieldID val="10"/>
                    <WithValue val="9"/>
                    <Incremental val="N"/>
                    <ForcedUpdate val="Y"/>
                    <Condition val="Y"/>
                    <Modifier val="B"/>
                    <Direction val="C"/>
                  </Update>
                </LogicLine>
                <LogicLine>
                  <Update FlowIsn="165">
                    <Parent val="32768"/>
                    <FieldID val="11"/>
                    <WithValue val="10"/>
                    <Incremental val="N"/>
                    <ForcedUpdate val="Y"/>
                    <Condition val="Y"/>
                    <Modifier val="B"/>
                    <Direction val="C"/>
                  </Update>
                </LogicLine>
                <LogicLine>
                  <Update FlowIsn="166">
                    <Parent val="32768"/>
                    <FieldID val="12"/>
                    <WithValue val="11"/>
                    <Incremental val="N"/>
                    <ForcedUpdate val="Y"/>
                    <Condition val="Y"/>
                    <Modifier val="B"/>
                    <Direction val="C"/>
                  </Update>
                </LogicLine>
                <LogicLine>
                  <Update FlowIsn="167">
                    <Parent val="32768"/>
                    <FieldID val="13"/>
                    <WithValue val="8"/>
                    <Incremental val="N"/>
                    <ForcedUpdate val="Y"/>
                    <Condition val="Y"/>
                    <Modifier val="B"/>
                    <Direction val="C"/>
                  </Update>
                </LogicLine>
                <LogicLine>
                  <Update FlowIsn="168">
                    <Parent val="32768"/>
                    <FieldID val="14"/>
                    <WithValue val="9"/>
                    <Incremental val="N"/>
                    <ForcedUpdate val="Y"/>
                    <Condition val="Y"/>
                    <Modifier val="B"/>
                    <Direction val="C"/>
                  </Update>
                </LogicLine>
                <LogicLine>
                  <Update FlowIsn="169">
                    <Parent val="32768"/>
                    <FieldID val="15"/>
                    <WithValue val="10"/>
                    <Incremental val="N"/>
                    <ForcedUpdate val="Y"/>
                    <Condition val="Y"/>
                    <Modifier val="B"/>
                    <Direction val="C"/>
                  </Update>
                </LogicLine>
                <LogicLine>
                  <Update FlowIsn="170">
                    <Parent val="32768"/>
                    <FieldID val="16"/>
                    <WithValue val="11"/>
                    <Incremental val="N"/>
                    <ForcedUpdate val="Y"/>
                    <Condition val="Y"/>
                    <Modifier val="B"/>
                    <Direction val="C"/>
                  </Update>
                </LogicLine>
                <LogicLine>
                  <Update FlowIsn="368">
                    <Parent val="32768"/>
                    <FieldID val="145"/>
                    <WithValue val="8"/>
                    <Incremental val="N"/>
                    <ForcedUpdate val="Y"/>
                    <Condition val="Y"/>
                    <Modifier val="B"/>
                    <Direction val="C"/>
                  </Update>
                </LogicLine>
                <LogicLine>
                  <Update FlowIsn="369">
                    <Parent val="32768"/>
                    <FieldID val="146"/>
                    <WithValue val="9"/>
                    <Incremental val="N"/>
                    <ForcedUpdate val="Y"/>
                    <Condition val="Y"/>
                    <Modifier val="B"/>
                    <Direction val="C"/>
                  </Update>
                </LogicLine>
                <LogicLine>
                  <Update FlowIsn="370">
                    <Parent val="32768"/>
                    <FieldID val="147"/>
                    <WithValue val="10"/>
                    <Incremental val="N"/>
                    <ForcedUpdate val="Y"/>
                    <Condition val="Y"/>
                    <Modifier val="B"/>
                    <Direction val="C"/>
                  </Update>
                </LogicLine>
                <LogicLine>
                  <Update FlowIsn="371">
                    <Parent val="32768"/>
                    <FieldID val="148"/>
                    <WithValue val="11"/>
                    <Incremental val="N"/>
                    <ForcedUpdate val="Y"/>
                    <Condition val="Y"/>
                    <Modifier val="B"/>
                    <Direction val="C"/>
                  </Update>
                </LogicLine>
                <LogicLine>
                  <Update FlowIsn="213">
                    <Parent val="32768"/>
                    <FieldID val="149"/>
                    <WithValue val="28"/>
                    <Incremental val="N"/>
                    <ForcedUpdate val="Y"/>
                    <Condition val="Y"/>
                    <Modifier val="B"/>
                    <Direction val="C"/>
                  </Update>
                </LogicLine>
                <LogicLine>
                  <Evaluate FlowIsn="308">
                    <Expression val="31"/>
                    <Condition val="Y"/>
                    <Modifier val="B"/>
                    <Direction val="C"/>
                  </Evaluate>
                </LogicLine>
                <LogicLine>
                  <Evaluate FlowIsn="309">
                    <Expression val="33"/>
                    <Condition Exp="34"/>
                    <Modifier val="B"/>
                    <Direction val="C"/>
                  </Evaluate>
                </LogicLine>
                <LogicLine>
                  <Evaluate FlowIsn="361">
                    <Expression val="36"/>
                    <Condition Exp="37"/>
                    <Modifier val="B"/>
                    <Direction val="C"/>
                  </Evaluate>
                </LogicLine>
                <LogicLine>
                  <Update FlowIsn="355">
                    <Parent val="32768"/>
                    <FieldID val="1471"/>
                    <WithValue val="35"/>
                    <Incremental val="N"/>
                    <ForcedUpdate val="Y"/>
                    <Condition val="Y"/>
                    <Modifier val="B"/>
                    <Direction val="C"/>
                  </Update>
                </LogicLine>
                <LogicLine>
                  <CallTask FlowIsn="177">
                    <OperationType val="T"/>
                    <Event>
                      <EventType val="N"/>
                    </Event>
                    <TaskID comp="-1" obj="95"/>
                    <Lock val="N"/>
                    <Wait val="Y"/>
                    <SyncData val="N"/>
                    <RetainFocus val="N"/>
                    <Condition val="Y"/>
                    <Modifier val="S"/>
                    <Direction val="C"/>
                  </CallTask>
                </LogicLine>
                <LogicLine>
                  <CallTask FlowIsn="36">
                    <OperationType val="P"/>
                    <Event>
                      <EventType val="N"/>
                    </Event>
                    <TaskID comp="2" obj="2788"/>
                    <Lock val="N"/>
                    <Arguments>
                      <Argument>
                        <Parent val="32768"/>
                        <Variable val="1"/>
                        <Skip val="N"/>
                      </Argument>
                      <Argument>
                        <Parent val="32768"/>
                        <Variable val="2"/>
                        <Skip val="N"/>
                      </Argument>
                      <Argument>
                        <Parent val="32768"/>
                        <Variable val="3"/>
                        <Skip val="N"/>
                      </Argument>
                      <Argument>
                        <Parent val="32768"/>
                        <Variable val="4"/>
                        <Skip val="N"/>
                      </Argument>
                      <Argument>
                        <Parent val="32768"/>
                        <Variable val="5"/>
                        <Skip val="N"/>
                      </Argument>
                      <Argument>
                        <Parent val="32768"/>
                        <Variable val="6"/>
                        <Skip val="N"/>
                      </Argument>
                      <Argument>
                        <Parent val="32768"/>
                        <Variable val="7"/>
                        <Skip val="N"/>
                      </Argument>
                      <Argument>
                        <Parent val="32768"/>
                        <Variable val="8"/>
                        <Skip val="N"/>
                      </Argument>
                      <Argument>
                        <Parent val="32768"/>
                        <Variable val="1"/>
                        <Skip val="N"/>
                      </Argument>
                      <Argument>
                        <Parent val="32768"/>
                        <Variable val="2"/>
                        <Skip val="N"/>
                      </Argument>
                      <Argument>
                        <Parent val="32768"/>
                        <Variable val="3"/>
                        <Skip val="N"/>
                      </Argument>
                      <Argument>
                        <Parent val="32768"/>
                        <Variable val="4"/>
                        <Skip val="N"/>
                      </Argument>
                      <Argument>
                        <Parent val="32768"/>
                        <Variable val="1"/>
                        <Skip val="N"/>
                      </Argument>
                      <Argument>
                        <Parent val="32768"/>
                        <Variable val="2"/>
                        <Skip val="N"/>
                      </Argument>
                      <Argument>
                        <Parent val="32768"/>
                        <Variable val="3"/>
                        <Skip val="N"/>
                      </Argument>
                      <Argument>
                        <Parent val="32768"/>
                        <Variable val="4"/>
                        <Skip val="N"/>
                      </Argument>
                      <Argument>
                        <Parent val="32768"/>
                        <Variable val="24"/>
                        <Skip val="N"/>
                      </Argument>
                      <Argument>
                        <Parent val="32768"/>
                        <Variable val="21"/>
                        <Skip val="N"/>
                      </Argument>
                      <Argument>
                        <Skip val="Y"/>
                      </Argument>
                      <Argument>
                        <Skip val="Y"/>
                      </Argument>
                      <Argument>
                        <Skip val="Y"/>
                      </Argument>
                      <Argument>
                        <Skip val="Y"/>
                      </Argument>
                      <Argument>
                        <Skip val="Y"/>
                      </Argument>
                      <Argument>
                        <Skip val="Y"/>
                      </Argument>
                      <Argument>
                        <Skip val="Y"/>
                      </Argument>
                      <Argument>
                        <Skip val="Y"/>
                      </Argument>
                      <Argument>
                        <Skip val="Y"/>
                      </Argument>
                      <Argument>
                        <Skip val="Y"/>
                      </Argument>
                      <Argument>
                        <Skip val="Y"/>
                      </Argument>
                      <Argument>
                        <Skip val="Y"/>
                      </Argument>
                      <Argument>
                        <Skip val="Y"/>
                      </Argument>
                    </Arguments>
                    <Wait val="Y"/>
                    <SyncData val="N"/>
                    <RetainFocus val="N"/>
                    <Condition val="Y"/>
                    <Modifier val="B"/>
                    <Direction val="C"/>
                  </CallTask>
                </LogicLine>
                <LogicLine>
                  <CallTask FlowIsn="37">
                    <OperationType val="P"/>
                    <Event>
                      <EventType val="N"/>
                    </Event>
                    <TaskID comp="3" obj="259"/>
                    <Lock val="N"/>
                    <Arguments>
                      <Argument>
                        <Parent val="32768"/>
                        <Variable val="1"/>
                        <Skip val="N"/>
                      </Argument>
                      <Argument>
                        <Parent val="32768"/>
                        <Variable val="2"/>
                        <Skip val="N"/>
                      </Argument>
                      <Argument>
                        <Parent val="32768"/>
                        <Variable val="3"/>
                        <Skip val="N"/>
                      </Argument>
                      <Argument>
                        <Parent val="32768"/>
                        <Variable val="4"/>
                        <Skip val="N"/>
                      </Argument>
                      <Argument>
                        <Parent val="32768"/>
                        <Variable val="5"/>
                        <Skip val="N"/>
                      </Argument>
                      <Argument>
                        <Parent val="32768"/>
                        <Variable val="6"/>
                        <Skip val="N"/>
                      </Argument>
                      <Argument>
                        <Parent val="32768"/>
                        <Variable val="7"/>
                        <Skip val="N"/>
                      </Argument>
                      <Argument>
                        <Parent val="32768"/>
                        <Variable val="8"/>
                        <Skip val="N"/>
                      </Argument>
                      <Argument>
                        <Parent val="32768"/>
                        <Variable val="9"/>
                        <Skip val="N"/>
                      </Argument>
                      <Argument>
                        <Parent val="32768"/>
                        <Variable val="10"/>
                        <Skip val="N"/>
                      </Argument>
                      <Argument>
                        <Parent val="32768"/>
                        <Variable val="11"/>
                        <Skip val="N"/>
                      </Argument>
                      <Argument>
                        <Parent val="32768"/>
                        <Variable val="12"/>
                        <Skip val="N"/>
                      </Argument>
                      <Argument>
                        <Parent val="32768"/>
                        <Variable val="13"/>
                        <Skip val="N"/>
                      </Argument>
                      <Argument>
                        <Parent val="32768"/>
                        <Variable val="14"/>
                        <Skip val="N"/>
                      </Argument>
                      <Argument>
                        <Parent val="32768"/>
                        <Variable val="15"/>
                        <Skip val="N"/>
                      </Argument>
                      <Argument>
                        <Parent val="32768"/>
                        <Variable val="16"/>
                        <Skip val="N"/>
                      </Argument>
                      <Argument>
                        <Parent val="32768"/>
                        <Variable val="21"/>
                        <Skip val="N"/>
                      </Argument>
                      <Argument>
                        <Parent val="32768"/>
                        <Variable val="24"/>
                        <Skip val="N"/>
                      </Argument>
                    </Arguments>
                    <Wait val="Y"/>
                    <SyncData val="N"/>
                    <RetainFocus val="N"/>
                    <Condition val="Y"/>
                    <Modifier val="B"/>
                    <Direction val="C"/>
                  </CallTask>
                </LogicLine>
                <LogicLine>
                  <CallTask FlowIsn="40">
                    <OperationType val="P"/>
                    <Event>
                      <EventType val="N"/>
                    </Event>
                    <TaskID comp="-1" obj="3007"/>
                    <Lock val="N"/>
                    <Arguments>
                      <Argument>
                        <Expression val="17"/>
                        <Skip val="N"/>
                      </Argument>
                    </Arguments>
                    <Wait val="Y"/>
                    <SyncData val="N"/>
                    <RetainFocus val="N"/>
                    <Condition Exp="27"/>
                    <Modifier val="B"/>
                    <Direction val="C"/>
                  </CallTask>
                </LogicLine>
                <LogicLine>
                  <END_BLK FlowIsn="38"/>
                </LogicLine>
              </LogicLines>
            </LogicUnit>
          </TaskLogic>
          <TaskForms>
            <FormEntry id="1">
              <PropertyList model="FORM_GUI0">
                <_Comment id="218"/>
                <FormName id="311" valUnicode="Server Benutzer vorhanden"/>
              </PropertyList>
            </FormEntry>
          </TaskForms>
          <Expressions>
            <Expression id="1">
              <ExpSyntax val="Trim({38,11})"/>
              <ExpAttribute val="A"/>
            </Expression>
            <Expression id="37">
              <ExpSyntax val="{38,15}>0 AND Val(INIGet('ContextInactivityTimeout'),'9')>{38,15}"/>
              <ExpAttribute val="B"/>
            </Expression>
            <Expression id="31">
              <ExpSyntax val="INIPut('ContextInactivityTimeout='&amp;IF({0,43}>0,Trim(Str({0,43},'9')),'480000'),'FALSE'LOG)"/>
              <ExpAttribute val="B"/>
            </Expression>
            <Expression id="33">
              <ExpSyntax val="INIPut('ContextInactivityTimeout='&amp;Trim(Str({0,37},'9')),'FALSE'LOG)"/>
              <ExpAttribute val="B"/>
            </Expression>
            <Expression id="36">
              <ExpSyntax val="INIPut('ContextInactivityTimeout='&amp;Trim(Str({38,15},'9')),'FALSE'LOG)"/>
              <ExpAttribute val="B"/>
            </Expression>
            <Expression id="29">
              <ExpSyntax val="{0,8}"/>
              <ExpAttribute val="N"/>
            </Expression>
            <Expression id="28">
              <ExpSyntax val="{0,36}"/>
              <ExpAttribute val="N"/>
            </Expression>
            <Expression id="2">
              <ExpSyntax val="{0,4} AND Trim({38,11})>''"/>
              <ExpAttribute val="B"/>
            </Expression>
            <Expression id="3">
              <ExpSyntax val="{0,6}=1"/>
              <ExpAttribute val="B"/>
            </Expression>
            <Expression id="4">
              <ExpSyntax val="{0,7}={38,4} AND {38,4}>'' AND {0,7}>'' AND {38,4}&lt;>'daibv7Kq5Mk/ZYSaTsugIg==' AND {0,7}&lt;>'daibv7Kq5Mk/ZYSaTsugIg=='"/>
              <ExpAttribute val="B"/>
            </Expression>
            <Expression id="5">
              <ExpSyntax val="{0,1} AND NOT {0,3}"/>
              <ExpAttribute val="B"/>
            </Expression>
            <Expression id="6">
              <ExpSyntax val="Logon({38,11},'')"/>
              <ExpAttribute val="B"/>
            </Expression>
            <Expression id="7">
              <ExpSyntax val="{0,1} AND {0,3}"/>
              <ExpAttribute val="B"/>
            </Expression>
            <Expression id="8">
              <ExpSyntax val="{0,8}"/>
              <ExpAttribute val="N"/>
            </Expression>
            <Expression id="9">
              <ExpSyntax val="{0,9}"/>
              <ExpAttribute val="N"/>
            </Expression>
            <Expression id="10">
              <ExpSyntax val="{0,10}"/>
              <ExpAttribute val="N"/>
            </Expression>
            <Expression id="11">
              <ExpSyntax val="{0,11}"/>
              <ExpAttribute val="N"/>
            </Expression>
            <Expression id="12">
              <ExpSyntax val="{0,12}"/>
              <ExpAttribute val="N"/>
            </Expression>
            <Expression id="13">
              <ExpSyntax val="{0,13}"/>
              <ExpAttribute val="N"/>
            </Expression>
            <Expression id="14">
              <ExpSyntax val="{0,14}"/>
              <ExpAttribute val="N"/>
            </Expression>
            <Expression id="15">
              <ExpSyntax val="{0,15}"/>
              <ExpAttribute val="N"/>
            </Expression>
            <Expression id="16">
              <ExpSyntax val="'SF-Benutzer-Check, gefunden '&amp;IF({0,4},'ja','nein')&amp;' Startebenen: '&amp;Trim(Str({0,8},'3'))&amp;'/'&amp;Trim(Str({0,9},'4'))&amp;'/'&amp;Trim(Str({0,10},'4'))&amp;'/'&amp;Trim(Str({0,11},'4'))&amp;' Z: '&amp;Trim(Str({0,12},'3'))&amp;'/'&amp;Trim(Str({0,13},'4'))&amp;'/'&amp;Trim(Str({0,14},'4'))&amp;'/'&amp;Trim(Str({0,15},'4'))"/>
              <ExpAttribute val="A"/>
            </Expression>
            <Expression id="17">
              <ExpSyntax val="'SF-Benutzer-Check, Ebenen gesetzt: '&amp;Trim(Str({32768,1},'3'))&amp;'/'&amp;Trim(Str({32768,2},'4'))&amp;'/'&amp;Trim(Str({32768,3},'4'))&amp;'/'&amp;Trim(Str({32768,4},'4'))&amp;' Z: '&amp;Trim(Str({32768,5},'3'))&amp;'/'&amp;Trim(Str({32768,6},'4'))&amp;'/'&amp;Trim(Str({32768,7},'4'))&amp;'/'&amp;Trim(Str({32768,8},'4'))"/>
              <ExpAttribute val="A"/>
            </Expression>
            <Expression id="24">
              <ExpSyntax val="'PW_Server:'&amp;Trim({0,7})&amp;', PW_local:'&amp;Trim({38,4})"/>
              <ExpAttribute val="A"/>
            </Expression>
            <Expression id="25">
              <ExpSyntax val="'FALSE'LOG"/>
              <ExpAttribute val="B"/>
            </Expression>
            <Expression id="27">
              <ExpSyntax val="{32768,1166}"/>
              <ExpAttribute val="B"/>
            </Expression>
            <Expression id="30">
              <ExpSyntax val="1"/>
              <ExpAttribute val="N"/>
            </Expression>
            <Expression id="34">
              <ExpSyntax val="{0,37}>0"/>
              <ExpAttribute val="B"/>
            </Expression>
            <Expression id="35">
              <ExpSyntax val="Val(Trim(INIGet('ContextInactivityTimeout')),'9')"/>
              <ExpAttribute val="N"/>
            </Expression>
          </Expressions>
          <Task MainProgram="N">
            <Header Description="mitarbeiter nr" ISN_2="95" LastIsn="95" id="3321">
              <ExecutionRight comp="-1"/>
              <Resident val="Y"/>
              <SQL val="N"/>
              <ReturnValue>
                <ReturnValueAttr/>
                <ParametersAttributes/>
              </ReturnValue>
              <SqlWhereExist val="N"/>
              <TaskType val="B"/>
              <External val="N"/>
              <FormType val="N"/>
              <DotNetObjectExists val="N"/>
              <LastModified _date="737431" _time="51525" date="07.01.2020" time="14:18:45"/>
            </Header>
            <ItemIsn val="11"/>
            <Resource>
              <DB id="1">
                <DataObject comp="2" obj="108"/>
                <Access val="R"/>
                <Share val="W"/>
                <Open val="N"/>
                <Cache val="Y"/>
                <IdentifyRowModifications val="84"/>
              </DB>
              <Columns/>
            </Resource>
            <Information>
              <Key>
                <Mode val="N"/>
              </Key>
              <DB comp="-1"/>
              <Sort>
                <CLS val="A"/>
              </Sort>
              <ForceRecordDelete DEL="N"/>
              <EndTaskCondition val="Y"/>
              <EvaluateEndCondition val="A"/>
              <InitialMode val="M"/>
              <Locate Direction="A"/>
              <Range Direction="A"/>
              <VarRange/>
              <TaskProperties>
                <SelectionTable val="N"/>
                <ConfirmUpdate CNFU="N"/>
                <ConfirmCancel val="N"/>
                <ErrorStrategy val="A"/>
                <LockingStrategy val="I"/>
                <CacheStrategy val="T"/>
                <ForceRecordSuffix val="N"/>
                <TransactionMode val="W"/>
                <TransactionBegin val="T"/>
                <PreloadView val="N"/>
                <AllowEmptyDataview val="N"/>
                <KeepCreatedContext val="N"/>
              </TaskProperties>
              <SIDE_WIN>
                <AllowOptions val="N"/>
                <AllowQuery val="Y"/>
                <AllowModify val="Y"/>
                <AllowCreate val="Y"/>
                <AllowDelete val="Y"/>
                <AllowLocate val="Y"/>
                <AllowRange val="Y"/>
                <AllowIndexChange val="Y"/>
                <AllowSorting val="Y"/>
                <AllowIOFiles val="Y"/>
                <RecordCycle val="Y"/>
                <AllowEvents val="N"/>
                <AllowIndexOptimization val="Y"/>
                <AllowLocationInQuery val="Y"/>
                <AllowPrintingData val="N"/>
              </SIDE_WIN>
              <WIN>
                <OpenTaskWindow val="N"/>
                <CloseTaskWindow val="Y"/>
                <ForegroundWindow val="Y"/>
                <FlipFld val="N"/>
                <RefreshTaskWindow ReturnValue="N"/>
              </WIN>
              <BOX>
                <Direction val="V"/>
              </BOX>
            </Information>
            <INT_CMP_LIST_INFO>
              <v>2</v>
            </INT_CMP_LIST_INFO>
            <TaskLogic>
              <LogicUnit id="1" propagate="78">
                <Level val="R"/>
                <Type val="M"/>
                <Scope val="S"/>
                <EngineDirective val="S"/>
                <ShowMessage val="Y"/>
                <Condition val="89"/>
                <Event>
                  <EventType val="S"/>
                </Event>
                <LogicLines>
                  <LogicLine>
                    <DATAVIEW_SRC FlowIsn="1" Type="M">
                      <Condition val="N"/>
                      <Modifier val="B"/>
                      <Direction val="C"/>
                    </DATAVIEW_SRC>
                  </LogicLine>
                  <LogicLine>
                    <LNK Direction="A" EVL_CND="R" FlowIsn="2" Key="6" Mode="R" SortType="3" VIEW="1" VIEWS="7">
                      <DB comp="2" obj="108"/>
                      <Expanded val="1"/>
                      <Condition val="Y"/>
                    </LNK>
                  </LogicLine>
                  <LogicLine>
                    <Select FieldID="5" FlowIsn="8" id="5">
                      <Column val="1"/>
                      <Type val="R"/>
                      <ExposedToRoute val="N"/>
                      <IsParameter val="N"/>
                      <Locate MAX="1" MIN="1"/>
                      <DIFF_UPDATE val="T"/>
                      <Condition val="N"/>
                      <Modifier val="S"/>
                      <Direction val="C"/>
                    </Select>
                  </LogicLine>
                  <LogicLine>
                    <Select FieldID="4" FlowIsn="7" id="4">
                      <Column val="2"/>
                      <Type val="R"/>
                      <ExposedToRoute val="N"/>
                      <IsParameter val="N"/>
                      <Locate MAX="2" MIN="2"/>
                      <DIFF_UPDATE val="T"/>
                      <Condition val="N"/>
                      <Modifier val="S"/>
                      <Direction val="C"/>
                    </Select>
                  </LogicLine>
                  <LogicLine>
                    <Select FieldID="3" FlowIsn="6" id="3">
                      <Column val="3"/>
                      <Type val="R"/>
                      <ExposedToRoute val="N"/>
                      <IsParameter val="N"/>
                      <Locate MAX="3" MIN="3"/>
                      <DIFF_UPDATE val="T"/>
                      <Condition val="N"/>
                      <Modifier val="S"/>
                      <Direction val="C"/>
                    </Select>
                  </LogicLine>
                  <LogicLine>
                    <Select FieldID="2" FlowIsn="5" id="2">
                      <Column val="4"/>
                      <Type val="R"/>
                      <ExposedToRoute val="N"/>
                      <IsParameter val="N"/>
                      <Locate MAX="4" MIN="4"/>
                      <DIFF_UPDATE val="T"/>
                      <Condition val="N"/>
                      <Modifier val="S"/>
                      <Direction val="C"/>
                    </Select>
                  </LogicLine>
                  <LogicLine>
                    <Select FieldID="7" FlowIsn="10" id="7">
                      <Column val="23"/>
                      <Type val="R"/>
                      <ExposedToRoute val="N"/>
                      <IsParameter val="N"/>
                      <Locate MAX="6" MIN="6"/>
                      <DIFF_UPDATE val="T"/>
                      <Condition val="N"/>
                      <Modifier val="S"/>
                      <Direction val="C"/>
                    </Select>
                  </LogicLine>
                  <LogicLine>
                    <Select FieldID="6" FlowIsn="9" id="6">
                      <Column val="7"/>
                      <Type val="R"/>
                      <ExposedToRoute val="N"/>
                      <IsParameter val="N"/>
                      <DIFF_UPDATE val="T"/>
                      <Condition val="N"/>
                      <Modifier val="S"/>
                      <Direction val="C"/>
                    </Select>
                  </LogicLine>
                  <LogicLine>
                    <Select FieldID="1" FlowIsn="4" id="1">
                      <Column val="5"/>
                      <Type val="R"/>
                      <ExposedToRoute val="N"/>
                      <IsParameter val="N"/>
                      <DIFF_UPDATE val="T"/>
                      <Condition val="N"/>
                      <Modifier val="S"/>
                      <Direction val="C"/>
                    </Select>
                  </LogicLine>
                  <LogicLine>
                    <END_LINK FlowIsn="3"/>
                  </LogicLine>
                </LogicLines>
              </LogicUnit>
              <LogicUnit id="2" propagate="78">
                <Level val="R"/>
                <Type val="S"/>
                <Scope val="S"/>
                <EngineDirective val="S"/>
                <ShowMessage val="Y"/>
                <Condition val="89"/>
                <Event>
                  <EventType val="S"/>
                </Event>
                <Expanded val="1"/>
                <LogicLines>
                  <LogicLine>
                    <Update FlowIsn="15">
                      <Parent val="32768"/>
                      <FieldID val="21"/>
                      <WithValue val="5"/>
                      <Incremental val="N"/>
                      <ForcedUpdate val="Y"/>
                      <Condition val="Y"/>
                      <Modifier val="B"/>
                      <Direction val="C"/>
                    </Update>
                  </LogicLine>
                  <LogicLine>
                    <Update FlowIsn="17">
                      <Parent val="32768"/>
                      <FieldID val="24"/>
                      <WithValue val="7"/>
                      <Incremental val="N"/>
                      <ForcedUpdate val="Y"/>
                      <Condition val="Y"/>
                      <Modifier val="B"/>
                      <Direction val="C"/>
                    </Update>
                  </LogicLine>
                </LogicLines>
              </LogicUnit>
            </TaskLogic>
            <TaskForms>
              <FormEntry id="1">
                <PropertyList model="FORM_GUI0">
                  <_Comment id="218"/>
                  <FormName id="311" valUnicode="mitarbeiter nr"/>
                </PropertyList>
              </FormEntry>
            </TaskForms>
            <Expressions>
              <Expression id="1">
                <ExpSyntax val="{32768,5}"/>
                <ExpAttribute val="N"/>
              </Expression>
              <Expression id="7">
                <ExpSyntax val="{0,7}"/>
                <ExpAttribute val="A"/>
              </Expression>
              <Expression id="2">
                <ExpSyntax val="{32768,6}"/>
                <ExpAttribute val="N"/>
              </Expression>
              <Expression id="3">
                <ExpSyntax val="{32768,7}"/>
                <ExpAttribute val="N"/>
              </Expression>
              <Expression id="4">
                <ExpSyntax val="{32768,8}"/>
                <ExpAttribute val="N"/>
              </Expression>
              <Expression id="5">
                <ExpSyntax val="{0,1}"/>
                <ExpAttribute val="N"/>
              </Expression>
              <Expression id="6">
                <ExpSyntax val="{38,11}"/>
                <ExpAttribute val="A"/>
              </Expression>
            </Expressions>
          </Task>
        </Task>
      </Task>
    </Programs>
  </ProgramsRepository>

</Application>
