<?xml version="1.0" encoding="UTF-8" standalone="no" ?>
<Application>

  <Header>
    <Version val="14070.00"/>
    <WithIsn val="Y"/>
    <LastIsn val="2"/>
    <LastIsnFolder val="0"/>
  </Header>

  <RightsRepository>
    <Rights>
      <Right id="1" name="nurCRMTeam">
        <PublicRight val="Y"/>
        <Key val="NCRM1420"/>
      </Right>
      <Right id="2" name="Varianten">
        <PublicRight val="Y"/>
        <Key val="VAR271"/>
      </Right>
    </Rights>
  </RightsRepository>

</Application>
